{
  "putin": 7,
  "china": 7,
  "guevara": 9,
  "linkedin": 7,
  "abused": 14,
  "day": 7,
  "wildfire": 7,
  "journalist": 7,
  "warring": 7,
  "corruption": 12,
  "rape": 14,
  "fox": 13,
  "court": 12,
  "imran": 12,
  "mccarthy": 17,
  "ambassador": 7,
  "general": 9,
  "donald": 14,
  "conservatives": 11,
  "liable": 14,
  "islamabad": 12,
  "texas": 16,
  "ural": 7,
  "talks": 7,
  "carroll": 14,
  "arabia": 8,
  "billion": 7,
  "ukraine": 7,
  "captured": 9,
  "mountains": 7,
  "twitter": 13,
  "kill": 10,
  "biden": 17,
  "violence": 12,
  "guinea": 17,
  "war": 7,
  "russian": 7,
  "debt": 17,
  "airstrikes": 10,
  "trump": 14,
  "arman": 7,
  "victory": 7,
  "israel": 10,
  "carlson": 13,
  "victims": 16,
  "tat": 15,
  "jihad": 10,
  "tit": 15,
  "shooting": 16,
  "reopen": 8,
  "arrest": 12,
  "diplomat": 15,
  "announces": 7,
  "istanbul": 14,
  "jobs": 7,
  "buried": 9,
  "che": 9,
  "turkey": 14,
  "israeli": 10,
  "canadian": 15,
  "khan": 12,
  "parade": 7,
  "sudan": 7,
  "trial": 14,
  "pakistani": 12,
  "toll": 7,
  "mall": 16,
  "syria": 8,
  "supporters": 12,
  "arrested": 12,
  "chile": 11,
  "papua": 17,
  "soldin": 7,
  "aid": 7,
  "saudi": 8,
  "militants": 10,
  "death": 7,
  "constitution": 11,
  "bombing": 14,
  "rewrite": 11,
  "islamic": 10,
  "protests": 12,
  "pakistan": 12,
  "afp": 7,
  "killed": 7,
  "strikes": 10,
  "russia": 7,
  "jury": 14,
  "gaza": 10,
  "tucker": 13
}