[
  {
    "story": "hong-kong-lai",
    "articles": 13,
    "agencies": 11
  },
  {
    "story": "dresden-german-hostage",
    "articles": 31,
    "agencies": 10
  },
  {
    "story": "fraud-hong-kong",
    "articles": 14,
    "agencies": 9
  },
  {
    "story": "explosion-jersey-missing",
    "articles": 13,
    "agencies": 9
  },
  {
    "story": "dies-journalist-qatar",
    "articles": 28,
    "agencies": 8
  },
  {
    "story": "corruption-peru-pledge",
    "articles": 16,
    "agencies": 8
  },
  {
    "story": "nobel-prize-ukraine",
    "articles": 10,
    "agencies": 8
  },
  {
    "story": "cabinet-peru-pledge",
    "articles": 15,
    "agencies": 7
  },
  {
    "story": "cabinet-corruption-peru",
    "articles": 15,
    "agencies": 7
  },
  {
    "story": "cabinet-peru-president",
    "articles": 15,
    "agencies": 7
  },
  {
    "story": "cabinet-corruption-pledge",
    "articles": 15,
    "agencies": 7
  },
  {
    "story": "dead-explosion-jersey",
    "articles": 9,
    "agencies": 7
  },
  {
    "story": "bakhmut-russia-ukraine",
    "articles": 28,
    "agencies": 6
  },
  {
    "story": "dies-qatar-wahl",
    "articles": 26,
    "agencies": 6
  },
  {
    "story": "peru-pledge-president",
    "articles": 14,
    "agencies": 6
  },
  {
    "story": "cabinet-pledge-president",
    "articles": 14,
    "agencies": 6
  },
  {
    "story": "dresden-hostage-police",
    "articles": 14,
    "agencies": 6
  },
  {
    "story": "dresden-german-police",
    "articles": 14,
    "agencies": 6
  },
  {
    "story": "cabinet-corruption-president",
    "articles": 14,
    "agencies": 6
  },
  {
    "story": "corruption-pledge-president",
    "articles": 14,
    "agencies": 6
  },
  {
    "story": "corruption-peru-president",
    "articles": 14,
    "agencies": 6
  },
  {
    "story": "german-hostage-police",
    "articles": 14,
    "agencies": 6
  },
  {
    "story": "hong-jailed-kong",
    "articles": 9,
    "agencies": 6
  },
  {
    "story": "dead-explosion-missing",
    "articles": 8,
    "agencies": 6
  },
  {
    "story": "dead-jersey-missing",
    "articles": 8,
    "agencies": 6
  },
  {
    "story": "fraud-hong-lai",
    "articles": 7,
    "agencies": 6
  },
  {
    "story": "fraud-kong-lai",
    "articles": 7,
    "agencies": 6
  },
  {
    "story": "dies-journalist-wahl",
    "articles": 25,
    "agencies": 5
  },
  {
    "story": "journalist-qatar-wahl",
    "articles": 25,
    "agencies": 5
  },
  {
    "story": "iran-russia-ukraine",
    "articles": 15,
    "agencies": 5
  },
  {
    "story": "nobel-peace-ukraine",
    "articles": 13,
    "agencies": 5
  },
  {
    "story": "stake-syria-turkey",
    "articles": 11,
    "agencies": 5
  },
  {
    "story": "escalation-stake-syria",
    "articles": 11,
    "agencies": 5
  },
  {
    "story": "bakhmut-destroyed-ukraine",
    "articles": 8,
    "agencies": 5
  },
  {
    "story": "explosion-island-jersey",
    "articles": 7,
    "agencies": 5
  },
  {
    "story": "bombing-pakistan-wounds",
    "articles": 6,
    "agencies": 5
  },
  {
    "story": "bombing-kills-pakistan",
    "articles": 6,
    "agencies": 5
  },
  {
    "story": "bakery-kills-wounds",
    "articles": 6,
    "agencies": 5
  },
  {
    "story": "bakery-pakistan-wounds",
    "articles": 6,
    "agencies": 5
  },
  {
    "story": "bombing-kills-wounds",
    "articles": 6,
    "agencies": 5
  },
  {
    "story": "kills-pakistan-wounds",
    "articles": 6,
    "agencies": 5
  },
  {
    "story": "bakery-bombing-wounds",
    "articles": 6,
    "agencies": 5
  },
  {
    "story": "bakery-bombing-pakistan",
    "articles": 6,
    "agencies": 5
  },
  {
    "story": "bakery-bombing-kills",
    "articles": 6,
    "agencies": 5
  },
  {
    "story": "iran-partnership-russia",
    "articles": 6,
    "agencies": 5
  },
  {
    "story": "bakery-kills-pakistan",
    "articles": 6,
    "agencies": 5
  },
  {
    "story": "arizona-kari-lake",
    "articles": 5,
    "agencies": 5
  },
  {
    "story": "jailed-kong-lai",
    "articles": 5,
    "agencies": 5
  },
  {
    "story": "hong-jailed-lai",
    "articles": 5,
    "agencies": 5
  },
  {
    "story": "morocco-portugal-semifinals",
    "articles": 5,
    "agencies": 5
  },
  {
    "story": "bakhmut-ruins-ukraine",
    "articles": 19,
    "agencies": 4
  },
  {
    "story": "city-dresden-hostage",
    "articles": 18,
    "agencies": 4
  },
  {
    "story": "city-dresden-german",
    "articles": 14,
    "agencies": 4
  },
  {
    "story": "city-german-hostage",
    "articles": 14,
    "agencies": 4
  },
  {
    "story": "russia-ukraine-war",
    "articles": 13,
    "agencies": 4
  },
  {
    "story": "nobel-russia-ukraine",
    "articles": 13,
    "agencies": 4
  },
  {
    "story": "city-dresden-police",
    "articles": 12,
    "agencies": 4
  },
  {
    "story": "city-german-police",
    "articles": 12,
    "agencies": 4
  },
  {
    "story": "city-hostage-police",
    "articles": 12,
    "agencies": 4
  },
  {
    "story": "escalation-explainer-syria",
    "articles": 10,
    "agencies": 4
  },
  {
    "story": "escalation-explainer-stake",
    "articles": 10,
    "agencies": 4
  },
  {
    "story": "escalation-explainer-turkey",
    "articles": 10,
    "agencies": 4
  },
  {
    "story": "escalation-stake-turkey",
    "articles": 10,
    "agencies": 4
  },
  {
    "story": "escalation-syria-turkey",
    "articles": 10,
    "agencies": 4
  },
  {
    "story": "explainer-stake-turkey",
    "articles": 10,
    "agencies": 4
  },
  {
    "story": "explainer-syria-turkey",
    "articles": 10,
    "agencies": 4
  },
  {
    "story": "explainer-stake-syria",
    "articles": 10,
    "agencies": 4
  },
  {
    "story": "church-donation-unification",
    "articles": 9,
    "agencies": 4
  },
  {
    "story": "church-donation-japan",
    "articles": 9,
    "agencies": 4
  },
  {
    "story": "japan-unification-victims",
    "articles": 9,
    "agencies": 4
  },
  {
    "story": "church-japan-unification",
    "articles": 9,
    "agencies": 4
  },
  {
    "story": "church-japan-victims",
    "articles": 9,
    "agencies": 4
  },
  {
    "story": "church-donation-victims",
    "articles": 9,
    "agencies": 4
  },
  {
    "story": "donation-japan-unification",
    "articles": 9,
    "agencies": 4
  },
  {
    "story": "donation-japan-victims",
    "articles": 9,
    "agencies": 4
  },
  {
    "story": "church-unification-victims",
    "articles": 9,
    "agencies": 4
  },
  {
    "story": "donation-unification-victims",
    "articles": 9,
    "agencies": 4
  },
  {
    "story": "hong-kong-tycoon",
    "articles": 8,
    "agencies": 4
  },
  {
    "story": "bakhmut-grinds-ukraine",
    "articles": 7,
    "agencies": 4
  },
  {
    "story": "fraud-jailed-kong",
    "articles": 7,
    "agencies": 4
  },
  {
    "story": "fraud-hong-jailed",
    "articles": 7,
    "agencies": 4
  },
  {
    "story": "prize-putin-ukraine",
    "articles": 6,
    "agencies": 4
  },
  {
    "story": "nobel-prize-putin",
    "articles": 6,
    "agencies": 4
  },
  {
    "story": "invasion-nobel-ukraine",
    "articles": 6,
    "agencies": 4
  },
  {
    "story": "nobel-putin-ukraine",
    "articles": 6,
    "agencies": 4
  },
  {
    "story": "germany-mother-suspect",
    "articles": 5,
    "agencies": 4
  },
  {
    "story": "killing-mother-suspect",
    "articles": 5,
    "agencies": 4
  },
  {
    "story": "germany-hostages-mother",
    "articles": 5,
    "agencies": 4
  },
  {
    "story": "germany-hostages-suspect",
    "articles": 5,
    "agencies": 4
  },
  {
    "story": "germany-killing-mother",
    "articles": 5,
    "agencies": 4
  },
  {
    "story": "hostages-killing-mother",
    "articles": 5,
    "agencies": 4
  },
  {
    "story": "germany-hostages-killing",
    "articles": 5,
    "agencies": 4
  },
  {
    "story": "hostages-killing-suspect",
    "articles": 5,
    "agencies": 4
  },
  {
    "story": "hostages-mother-suspect",
    "articles": 5,
    "agencies": 4
  },
  {
    "story": "germany-killing-suspect",
    "articles": 5,
    "agencies": 4
  },
  {
    "story": "choir-ukrainian-war",
    "articles": 4,
    "agencies": 4
  },
  {
    "story": "choir-freedom-youth",
    "articles": 4,
    "agencies": 4
  },
  {
    "story": "choir-ukrainian-youth",
    "articles": 4,
    "agencies": 4
  },
  {
    "story": "choir-freedom-ukrainian",
    "articles": 4,
    "agencies": 4
  },
  {
    "story": "choir-freedom-war",
    "articles": 4,
    "agencies": 4
  }
]